aws_securityhub_suppression/__init__.py
aws_securityhub_suppression/account.py
aws_securityhub_suppression/cli/__init__.py
aws_securityhub_suppression/cli/commands/__init__.py
aws_securityhub_suppression/cli/commands/check.py
aws_securityhub_suppression/cli/commands/prepare.py
aws_securityhub_suppression/cli/commands/update.py
aws_securityhub_suppression/cli/context.py
aws_securityhub_suppression/cli/handler.py
aws_securityhub_suppression/documentation_generator.py
aws_securityhub_suppression/finding.py
aws_securityhub_suppression/schemas/__init__.py
aws_securityhub_suppression/schemas/environment.yaml
aws_securityhub_suppression/schemas/workload.yaml
aws_securityhub_suppression/suppress_findings.py
aws_securityhub_suppression/suppression.py
aws_securityhub_suppression/workload_generator.py
aws_securityhub_suppression-0.3.5.dist-info/LICENSE.txt
aws_securityhub_suppression-0.3.5.dist-info/METADATA
aws_securityhub_suppression-0.3.5.dist-info/WHEEL
aws_securityhub_suppression-0.3.5.dist-info/entry_points.txt
aws_securityhub_suppression-0.3.5.dist-info/RECORD
