Metadata-Version: 2.1
Name: aws-securityhub-suppression
Version: 0.3.5
Summary: 
License: MIT
Author: Joris Conijn
Author-email: Joris.Conijn@xebia.com
Requires-Python: >=3.9,<4.0
Classifier: License :: OSI Approved :: MIT License
Classifier: Programming Language :: Python :: 3
Classifier: Programming Language :: Python :: 3.9
Classifier: Programming Language :: Python :: 3.10
Classifier: Programming Language :: Python :: 3.11
Requires-Dist: click (>=8.1.3,<9.0.0)
Requires-Dist: jinja2 (>=3.1.2,<4.0.0)
Requires-Dist: jsonschema (>=4.18.3,<5.0.0)
Requires-Dist: landingzone-organization (>=0.8.0,<0.9.0)
Requires-Dist: pyyaml (>=6.0,<7.0)
Requires-Dist: xenon (>=0.9.0,<0.10.0)
